README.md
setup.py
aws_top/__init__.py
aws_top/__main__.py
aws_top/aws.py
aws_top/popup.py
aws_top/scroll.py
aws_top/signals.py
aws_top/window.py
aws_top.egg-info/PKG-INFO
aws_top.egg-info/SOURCES.txt
aws_top.egg-info/dependency_links.txt
aws_top.egg-info/entry_points.txt
aws_top.egg-info/requires.txt
aws_top.egg-info/top_level.txt