Metadata-Version: 1.0
Name: aws-top
Version: 0.4
Summary: CLI Dashboard for AWS services
Home-page: https://github.com/brennerm/aws-top
Author: brennerm
Author-email: xamrennerb@gmail.com
License: MIT
Platform: UNKNOWN
